AFZEWWVfxjXU2h86cGKbz2aXvLiWjuNqrhs5tPbf1cta9ZwGXVV2ow/__init__.py
AFZEWWVfxjXU2h86cGKbz2aXvLiWjuNqrhs5tPbf1cta9ZwGXVV2ow-0.0.1.dist-info/METADATA
AFZEWWVfxjXU2h86cGKbz2aXvLiWjuNqrhs5tPbf1cta9ZwGXVV2ow-0.0.1.dist-info/WHEEL
AFZEWWVfxjXU2h86cGKbz2aXvLiWjuNqrhs5tPbf1cta9ZwGXVV2ow-0.0.1.dist-info/top_level.txt
AFZEWWVfxjXU2h86cGKbz2aXvLiWjuNqrhs5tPbf1cta9ZwGXVV2ow-0.0.1.dist-info/RECORD
