Metadata-Version: 2.1
Name: AFZEWWVfxjXU2h86cGKbz2aXvLiWjuNqrhs5tPbf1cta9ZwGXVV2ow
Version: 0.0.1
Summary: My first Python package
Author: Alex Black
Author-email: ku113p@gmail.com
Keywords: python,first package
Classifier: Development Status :: 3 - Alpha
Classifier: Intended Audience :: Education
Classifier: Programming Language :: Python :: 2
Classifier: Programming Language :: Python :: 3
Classifier: Operating System :: MacOS :: MacOS X
Classifier: Operating System :: Microsoft :: Windows
